vader/__init__.py
vader/auth_resource.py
vader/azure.py
vader/consts.py
vader/core_service.py
vader/exceptions.py
vader/external.py
vader/general.py
vader/logging.py
vader/mongo.py
vader/mongo_resource.py
vader/policy_service.py
vader/project_resource.py
vader/raise_exception.py
vader/vault_resource.py
drizzutojr_vader-0.0.32.dist-info/METADATA
drizzutojr_vader-0.0.32.dist-info/WHEEL
drizzutojr_vader-0.0.32.dist-info/top_level.txt
drizzutojr_vader-0.0.32.dist-info/RECORD
