Metadata-Version: 2.1
Name: drizzutojr-vader
Version: 0.0.32
Summary: A library to be used with the Hashicorp Vault Vader Platform
Author: drizzutojr
License: MIT
Requires-Dist: drizzutojr-vapi (>=0.0.8)
Requires-Dist: semver (>=3.0.0)
Requires-Dist: pymongo (>=4.3.3)
Requires-Dist: msal (>=1.23.0)
Requires-Dist: python-json-logger (>=2.0.7)
